{"nodes": [{"id": "gym_list_screen_gymlistscreen", "label": "GymListScreen", "file_type": "code", "source_file": "lib/features/gyms/presentation/screens/gym_list_screen.dart", "source_location": null, "source_url": null, "captured_at": null, "author": null, "contributor": null}], "edges": [{"source": "gym_list_screen_gymlistscreen", "target": "gym_list_provider_gymlistprovider", "relation": "calls", "confidence": "EXTRACTED", "confidence_score": 1.0, "source_file": "lib/features/gyms/presentation/screens/gym_list_screen.dart", "source_location": "29", "weight": 1.0}, {"source": "gym_list_screen_gymlistscreen", "target": "gym_models_gym", "relation": "references", "confidence": "EXTRACTED", "confidence_score": 1.0, "source_file": "lib/features/gyms/presentation/screens/gym_list_screen.dart", "source_location": "150", "weight": 1.0}], "hyperedges": []}